junon/__init__.py
junon/assistants/__init__.py
junon/assistants/data_analytics.py
junon/assistants/writing_assistant.py
junon/llm_util.py
junon/util/__init__.py
junon/util/ai_config_util.py
junon/util/conversation_history_util.py
junon/util/gpt_stream_parser.py
junon/util/log_util.py
junon/util/nb_util.py
junon/util/structured_data.py
junon-0.1.1.dist-info/METADATA
junon-0.1.1.dist-info/WHEEL
junon-0.1.1.dist-info/RECORD
