Metadata-Version: 2.1
Name: junon
Version: 0.1.1
Summary: 
Author: tokoi
Author-email: mkt.tokoi@gmail.com
Requires-Python: >=3.9,<4.0
Classifier: Programming Language :: Python :: 3
Classifier: Programming Language :: Python :: 3.9
Classifier: Programming Language :: Python :: 3.10
Classifier: Programming Language :: Python :: 3.11
Requires-Dist: ipywidgets (>=8.1.1,<9.0.0)
Requires-Dist: jupyter (>=1.0.0,<2.0.0)
Requires-Dist: openai (>=1.6.1,<2.0.0)
Requires-Dist: overrides (>=7.6.0,<8.0.0)
Requires-Dist: tiktoken (>=0.5.2,<0.6.0)
